Metadata-Version: 2.1
Name: kewpie
Version: 0.0.2
Summary: KEyWord PIckEr with tf-idf
Home-page: https://github.com/sobamchan/kewpie
Author: Sotaro Takeshita
Author-email: oh.sore.sore.soutarou@gmail.com
License: MIT
Platform: UNKNOWN
Classifier: Programming Language :: Python :: 3.6
Classifier: Programming Language :: Python :: 3.7
